Workbook

Sheet Compliance Summary
A1: CMDB Compliance Summary — CSDM v5 Enhanced (3K, Moderate >70%)
A3: Overall Metrics
A4: Metric | B4: Value
A5: Total CIs | B5: =COUNTA('CMDB CIs'!A2:A3001)
A6: Compliant | B6: =COUNTIF('CMDB CIs'!AE2:AE3001,"Compliant")
A7: Partially Compliant | B7: =COUNTIF('CMDB CIs'!AE2:AE3001,"Partially Compliant")
A8: Non-Compliant | B8: =COUNTIF('CMDB CIs'!AE2:AE3001,"Non-Compliant")
A9: Overall Compliance % | B9: =B6/B5
A10: Average Compliance Score | B10: =AVERAGE('CMDB CIs'!AD2:AD3001)
A13: Compliance by Business Application (CSDM v5)
A14: Business Application | B14: Total | C14: Compliant | D14: Non-Compliant | E14: Compliance %
A15: Workday | B15: =COUNTIF('CMDB CIs'!Z2:Z3001,A15) | C15: =COUNTIFS('CMDB CIs'!Z2:Z3001,A15,'CMDB CIs'!AE2:AE3001,"Compliant") | D15: =COUNTIFS('CMDB CIs'!Z2:Z3001,A15,'CMDB CIs'!AE2:AE3001,"Non-Compliant") | E15: =IFERROR(C15/B15,0)
A16: SAP ERP | B16: =COUNTIF('CMDB CIs'!Z2:Z3001,A16) | C16: =COUNTIFS('CMDB CIs'!Z2:Z3001,A16,'CMDB CIs'!AE2:AE3001,"Compliant") | D16: =COUNTIFS('CMDB CIs'!Z2:Z3001,A16,'CMDB CIs'!AE2:AE3001,"Non-Compliant") | E16: =IFERROR(C16/B16,0)
A17: Microsoft 365 | B17: =COUNTIF('CMDB CIs'!Z2:Z3001,A17) | C17: =COUNTIFS('CMDB CIs'!Z2:Z3001,A17,'CMDB CIs'!AE2:AE3001,"Compliant") | D17: =COUNTIFS('CMDB CIs'!Z2:Z3001,A17,'CMDB CIs'!AE2:AE3001,"Non-Compliant") | E17: =IFERROR(C17/B17,0)
A18: Adobe | B18: =COUNTIF('CMDB CIs'!Z2:Z3001,A18) | C18: =COUNTIFS('CMDB CIs'!Z2:Z3001,A18,'CMDB CIs'!AE2:AE3001,"Compliant") | D18: =COUNTIFS('CMDB CIs'!Z2:Z3001,A18,'CMDB CIs'!AE2:AE3001,"Non-Compliant") | E18: =IFERROR(C18/B18,0)
A19: Oracle Fusion ERP | B19: =COUNTIF('CMDB CIs'!Z2:Z3001,A19) | C19: =COUNTIFS('CMDB CIs'!Z2:Z3001,A19,'CMDB CIs'!AE2:AE3001,"Compliant") | D19: =COUNTIFS('CMDB CIs'!Z2:Z3001,A19,'CMDB CIs'!AE2:AE3001,"Non-Compliant") | E19: =IFERROR(C19/B19,0)
A22: Compliance by CI Class
A23: CI Class | B23: Total | C23: Compliant | D23: Non-Compliant | E23: Compliance %
A24: cmdb_ci_pc_hardware | B24: =COUNTIF('CMDB CIs'!C2:C3001,A24) | C24: =COUNTIFS('CMDB CIs'!C2:C3001,A24,'CMDB CIs'!AE2:AE3001,"Compliant") | D24: =COUNTIFS('CMDB CIs'!C2:C3001,A24,'CMDB CIs'!AE2:AE3001,"Non-Compliant") | E24: =IFERROR(C24/B24,0)
A25: cmdb_ci_linux_server | B25: =COUNTIF('CMDB CIs'!C2:C3001,A25) | C25: =COUNTIFS('CMDB CIs'!C2:C3001,A25,'CMDB CIs'!AE2:AE3001,"Compliant") | D25: =COUNTIFS('CMDB CIs'!C2:C3001,A25,'CMDB CIs'!AE2:AE3001,"Non-Compliant") | E25: =IFERROR(C25/B25,0)
A26: cmdb_ci_win_server | B26: =COUNTIF('CMDB CIs'!C2:C3001,A26) | C26: =COUNTIFS('CMDB CIs'!C2:C3001,A26,'CMDB CIs'!AE2:AE3001,"Compliant") | D26: =COUNTIFS('CMDB CIs'!C2:C3001,A26,'CMDB CIs'!AE2:AE3001,"Non-Compliant") | E26: =IFERROR(C26/B26,0)
A27: cmdb_ci_vmware_instance | B27: =COUNTIF('CMDB CIs'!C2:C3001,A27) | C27: =COUNTIFS('CMDB CIs'!C2:C3001,A27,'CMDB CIs'!AE2:AE3001,"Compliant") | D27: =COUNTIFS('CMDB CIs'!C2:C3001,A27,'CMDB CIs'!AE2:AE3001,"Non-Compliant") | E27: =IFERROR(C27/B27,0)
A28: cmdb_ci_db_instance | B28: =COUNTIF('CMDB CIs'!C2:C3001,A28) | C28: =COUNTIFS('CMDB CIs'!C2:C3001,A28,'CMDB CIs'!AE2:AE3001,"Compliant") | D28: =COUNTIFS('CMDB CIs'!C2:C3001,A28,'CMDB CIs'!AE2:AE3001,"Non-Compliant") | E28: =IFERROR(C28/B28,0)
A29: cmdb_ci_web_server | B29: =COUNTIF('CMDB CIs'!C2:C3001,A29) | C29: =COUNTIFS('CMDB CIs'!C2:C3001,A29,'CMDB CIs'!AE2:AE3001,"Compliant") | D29: =COUNTIFS('CMDB CIs'!C2:C3001,A29,'CMDB CIs'!AE2:AE3001,"Non-Compliant") | E29: =IFERROR(C29/B29,0)
A30: cmdb_ci_app_server | B30: =COUNTIF('CMDB CIs'!C2:C3001,A30) | C30: =COUNTIFS('CMDB CIs'!C2:C3001,A30,'CMDB CIs'!AE2:AE3001,"Compliant") | D30: =COUNTIFS('CMDB CIs'!C2:C3001,A30,'CMDB CIs'!AE2:AE3001,"Non-Compliant") | E30: =IFERROR(C30/B30,0)
A31: cmdb_ci_ip_switch | B31: =COUNTIF('CMDB CIs'!C2:C3001,A31) | C31: =COUNTIFS('CMDB CIs'!C2:C3001,A31,'CMDB CIs'!AE2:AE3001,"Compliant") | D31: =COUNTIFS('CMDB CIs'!C2:C3001,A31,'CMDB CIs'!AE2:AE3001,"Non-Compliant") | E31: =IFERROR(C31/B31,0)
A32: cmdb_ci_service_auto | B32: =COUNTIF('CMDB CIs'!C2:C3001,A32) | C32: =COUNTIFS('CMDB CIs'!C2:C3001,A32,'CMDB CIs'!AE2:AE3001,"Compliant") | D32: =COUNTIFS('CMDB CIs'!C2:C3001,A32,'CMDB CIs'!AE2:AE3001,"Non-Compliant") | E32: =IFERROR(C32/B32,0)
A33: cmdb_ci_storage_device | B33: =COUNTIF('CMDB CIs'!C2:C3001,A33) | C33: =COUNTIFS('CMDB CIs'!C2:C3001,A33,'CMDB CIs'!AE2:AE3001,"Compliant") | D33: =COUNTIFS('CMDB CIs'!C2:C3001,A33,'CMDB CIs'!AE2:AE3001,"Non-Compliant") | E33: =IFERROR(C33/B33,0)
A34: cmdb_ci_ip_router | B34: =COUNTIF('CMDB CIs'!C2:C3001,A34) | C34: =COUNTIFS('CMDB CIs'!C2:C3001,A34,'CMDB CIs'!AE2:AE3001,"Compliant") | D34: =COUNTIFS('CMDB CIs'!C2:C3001,A34,'CMDB CIs'!AE2:AE3001,"Non-Compliant") | E34: =IFERROR(C34/B34,0)
A35: cmdb_ci_ip_firewall | B35: =COUNTIF('CMDB CIs'!C2:C3001,A35) | C35: =COUNTIFS('CMDB CIs'!C2:C3001,A35,'CMDB CIs'!AE2:AE3001,"Compliant") | D35: =COUNTIFS('CMDB CIs'!C2:C3001,A35,'CMDB CIs'!AE2:AE3001,"Non-Compliant") | E35: =IFERROR(C35/B35,0)

Sheet CMDB CIs
A1: sys_id | B1: name | C1: sys_class_name | D1: asset_tag | E1: serial_number | F1: manufacturer | G1: model_id | H1: location | I1: environment | J1: install_status | K1: operational_status | L1: ip_address | M1: os | N1: os_version | O1: cpu_count | P1: ram_gb | Q1: disk_gb | R1: assigned_to | S1: assignment_group | T1: support_group | U1: owned_by | V1: managed_by | W1: first_discovered | X1: last_discovered | Y1: discovery_source | Z1: business_application | AA1: business_service | AB1: technical_application | AC1: technical_service | AD1: compliance_score | AE1: compliance_status | AF1: compliance_issues
A2: 20a9d63b44e64a69b8e59ef5333cde02 | B2: app-prd-ben-00001 | C2: cmdb_ci_app_server | D2: AST-71607316 | E2: SN2640065984 | F2: Apache Foundation | G2: Tomcat 10 | H2: Bengaluru-DC1 | I2: Production | J2: Installed | K2: Operational | L2: 10.38.96.24 | O2: 16 | P2: 256 | Q2: 500 | S2: Java Platform Team | T2: Java Platform Team | U2: Arjun Wilson | V2: Deepika Krishnan | W2: 2022-10-11 11:09:17 | X2: 2025-03-06 11:09:17 | Y2: CSV Import | Z2: SAP ERP | AA2: Record-to-Report | AB2: SAP S/4HANA Production | AC2: SAP Gateway OData Service | AD2: 90 | AE2: Compliant | AF2: Stale discovery (>90 days)
A3: d94fa50212a241eabde622d94b68d03b | B3: PC-0100001 | C3: cmdb_ci_pc_hardware | D3: AST-42754321 | E3: SN3808214504 | F3: Dell | G3: OptiPlex 7090 | J3: Installed | K3: Operational | L3: 10.158.35.59 | O3: 8 | P3: 32 | Q3: 1000 | R3: Kavita Reddy | S3: End User Computing | T3: End User Computing | U3: Suresh Jones | V3: Pooja Joshi | W3: 2023-12-09 11:09:17 | X3: 2026-05-09 11:09:17 | Y3: Service Mapping | Z3: Microsoft 365 | AA3: Internal Communications | AB3: SharePoint Online | AC3: Microsoft Endpoint Manager | AD3: 80 | AE3: Compliant | AF3: Missing environment; Missing location
A4: 6ad7d822d0cd4a96981276ba5996a37f | B4: sw-dev-hyd-00001 | C4: cmdb_ci_ip_switch | D4: AST-79713742 | F4: Cisco | G4: Nexus 9336C-FX2 | H4: Hyderabad-DC1 | I4: Development | J4: Installed | K4: Operational | L4: 10.138.137.94 | S4: Network Operations | T4: Network Operations | V4: Anand Iyer | W4: 2025-09-27 11:09:17 | X4: 2026-05-17 11:09:17 | Y4: Manual | Z4: Microsoft 365 | AA4: Internal Communications | AB4: Exchange Online | AC4: Microsoft Endpoint Manager | AD4: 80 | AE4: Compliant | AF4: Missing serial_number; Missing owned_by
A5: 1e4e075f495046b49ff3f15508315a3a | B5: PC-0100002 | C5: cmdb_ci_pc_hardware | D5: AST-38243358 | E5: SN5585622913 | F5: HP | G5: EliteBook 840 G10 | H5: Gurgaon-Office | I5: UAT | J5: Retired | K5: Operational | L5: 10.171.14.253 | O5: 6 | P5: 32 | Q5: 256 | R5: Ravi Brown | S5: Desktop Support | T5: Desktop Support | U5: Robert Shetty | V5: Deepika Krishnan | W5: 2023-09-12 11:09:17 | X5: 2026-05-03 11:09:17 | Y5: CSV Import | Z5: Microsoft 365 | AA5: Video Conferencing | AB5: SharePoint Online | AC5: Entra ID (Azure AD) | AD5: 100 | AE5: Compliant | AF5: None
A6: f4cbcbac109d4fe5bc86502f36ced604 | B6: PC-0100003 | C6: cmdb_ci_pc_hardware | D6: AST-46274203 | E6: SN4001009295 | F6: Lenovo | G6: ThinkPad T14 | H6: Pune-Office | I6: Production | J6: Installed | K6: Operational | L6: 10.35.4.13 | O6: 6 | P6: 8 | Q6: 256 | R6: Pooja Verma | S6: Desktop Support | T6: Desktop Support | U6: Rajesh Krishnan | V6: Robert Jones | W6: 2024-11-01 11:09:17 | X6: 2026-05-06 11:09:17 | Y6: CSV Import | Z6: Workday | AA6: HR Self-Service | AB6: Workday Recruiting Portal | AC6: HR Data Integration Bus | AD6: 100 | AE6: Compliant | AF6: None
A7: c6e65be05a7f49f39ff41f2b433d1b89 | B7: PC-0100004 | C7: cmdb_ci_pc_hardware | D7: AST-38725383 | E7: SN5348293994 | J7: In Maintenance | K7: DR Standby | L7: 10.50.52.62 | O7: 6 | P7: 32 | Q7: 256 | R7: Rohit Desai | S7: IT Service Desk | T7: IT Service Desk | U7: Meera Rao | V7: Aditya Mehta | W7: 2024-01-10 11:09:17 | X7: 2026-05-12 11:09:17 | Y7: CSV Import | Z7: Microsoft 365 | AA7: Internal Communications | AB7: Microsoft Purview | AC7: Microsoft Graph API | AD7: 60 | AE7: Partially Compliant | AF7: Missing manufacturer; Missing environment; Missing location; Missing model_id
A8: b807893685aa45e3b1a7a2d1c79da12b | B8: win-prd-pun-00001 | C8: cmdb_ci_win_server | D8: AST-88130076 | E8: SN6030620624 | F8: HPE | G8: ProLiant DL380 Gen10 | H8: Pune-Office | I8: Production | J8: Installed | K8: DR Standby | L8: 10.35.79.37 | M8: Windows Server | N8: 2022 Datacenter | O8: 96 | P8: 64 | Q8: 16000 | S8: Windows Admins | T8: Windows Admins | U8: Shreya Banerjee | V8: Neha Wilson | W8: 2024-12-07 11:09:17 | X8: 2026-05-12 11:09:17 | Y8: Manual | Z8: SAP ERP | AA8: Inventory & Warehouse | AB8: SAP S/4HANA Sales | AC8: SAP Solution Manager | AD8: 100 | AE8: Compliant | AF8: None
A9: 071eeff51e16479fb41ed4b1d6aaf559 | B9: PC-0100005 | C9: cmdb_ci_pc_hardware | D9: AST-90517524 | E9: SN2001360032 | F9: Dell | G9: OptiPlex 7090 | H9: Bengaluru-DC1 | I9: Test | J9: Installed | K9: Operational | L9: 10.139.237.94 | O9: 4 | P9: 8 | Q9: 256 | R9: John Singh | S9: IT Service Desk | T9: IT Service Desk | U9: Meera Mehta | V9: Shreya Desai | W9: 2023-09-11 11:09:17 | X9: 2026-05-20 11:09:17 | Y9: Manual | Z9: Microsoft 365 | AA9: Enterprise Email | AB9: Exchange Online | AC9: Entra ID (Azure AD) | AD9: 100 | AE9: Compliant | AF9: None
A10: 57403e0f073740958acd08b56378d6a2 | B10: app-uat-mum-00002 | C10: cmdb_ci_app_server | F10: Oracle | G10: WebLogic 14c | I10: UAT | J10: Installed | K10: Operational | L10: 10.188.91.158 | O10: 96 | P10: 16 | Q10: 200 | S10: Middleware Admins | U10: Anand Krishnan | V10: Meera Sharma | W10: 2024-11-26 11:09:17 | X10: 2026-05-13 11:09:17 | Y10: Manual | Z10: Oracle Fusion ERP | AA10: Project Portfolio Mgmt | AB10: Oracle Fusion Risk Mgmt | AC10: Oracle Integration Cloud | AD10: 60 | AE10: Partially Compliant | AF10: Missing serial_number; Missing support_group; Missing asset_tag; Missing location
A11: c4b5999414e145dab18f33c490f9beda | B11: vm-dev-pun-00001 | C11: cmdb_ci_vmware_instance | D11: AST-42703728 | F11: VMware | G11: vSphere VM | I11: Development | J11: Installed | K11: Operational | L11: 10.117.32.94 | M11: Windows Server | N11: 2022 Standard | O11: 4 | P11: 256 | Q11: 500 | S11: Virtualization Team | V11: Emma Sharma | W11: 2024-09-21 11:09:17 | X11: 2026-05-03 11:09:17 | Y11: BMC ADDM | Z11: Adobe | AA11: Marketing Automation | AB11: Adobe Creative Cloud | AC11: Adobe Asset Service | AD11: 60 | AE11: Partially Compliant | AF11: Missing support_group; Missing owned_by; Missing serial_number; Missing location
A12: 0ff7d04ecfae46ac91492f778a97f8fd | B12: lnx-prd-ben-00001 | C12: cmdb_ci_linux_server | D12: AST-39798329 | E12: SN5512298608 | F12: HPE | G12: ProLiant DL380 Gen10 | I12: Production | K12: Operational | L12: 10.18.205.10 | M12: Oracle Linux | N12: 8.7 | O12: 24 | P12: 32 | Q12: 2000 | S12: Platform Engineering | T12: Platform Engineering | U12: Michael Patel | V12: Karthik Shetty | W12: 2023-02-07 11:09:17 | X12: 2026-05-18 11:09:17 | Y12: CSV Import | Z12: Oracle Fusion ERP | AA12: Financial Close | AB12: Oracle Fusion Procurement | AC12: Oracle Analytics Cloud | AD12: 80 | AE12: Compliant | AF12: Missing location; Missing install_status
A13: dddc891f41d3467aadebdbe49ea6c208 | B13: vm-dr-ben-00002 | C13: cmdb_ci_vmware_instance | D13: AST-65777723 | E13: SN3376802437 | F13: VMware | G13: vSphere VM | H13: Bengaluru-DC1 | I13: DR | J13: Installed | K13: Operational | L13: 10.156.48.177 | M13: Windows Server | N13: 2022 Datacenter | O13: 4 | P13: 64 | Q13: 500 | S13: Cloud Operations | T13: Cloud Operations | U13: Aditya Williams | V13: John Sharma | W13: 2024-01-05 11:09:17 | X13: 2026-05-03 11:09:17 | Y13: BMC ADDM | Z13: Oracle Fusion ERP | AA13: Risk & Compliance | AB13: Oracle Fusion Tax Reporting | AC13: Oracle REST Data Service | AD13: 100 | AE13: Compliant | AF13: None
A14: 481370c138fd4c1fb358c723eb95b2ab | B14: sw-tst-mum-00002 | C14: cmdb_ci_ip_switch | E14: SN6019219960 | F14: Cisco | G14: Catalyst 9300-48P | H14: Mumbai-DC2 | K14: Operational | L14: 10.197.175.233 | S14: Network Engineering | T14: Network Engineering | V14: Meera Patel | W14: 2023-08-12 11:09:17 | X14: 2026-05-14 11:09:17 | Y14: SCCM | Z14: Workday | AA14: Time & Attendance | AB14: Workday HCM Core | AC14: Identity Federation (SAML) | AD14: 60 | AE14: Partially Compliant | AF14: Missing asset_tag; Missing owned_by; Missing install_status; Missing environment
A15: 39fd6ccde4d845469cb0a4285cf9fd6e | B15: PC-0100006 | C15: cmdb_ci_pc_hardware | D15: AST-66050915 | E15: SN7391581182 | F15: HP | G15: EliteBook 840 G10 | H15: Bengaluru-DC2 | J15: Installed | K15: Operational | L15: 10.40.47.254 | O15: 4 | P15: 16 | Q15: 1000 | R15: Neha Joshi | S15: IT Service Desk | T15: IT Service Desk | U15: Priya Verma | V15: Kavita Banerjee | W15: 2026-01-31 11:09:17 | X15: 2026-05-09 11:09:17 | Y15: Manual | Z15: Microsoft 365 | AA15: Enterprise Email | AB15: Microsoft Teams | AC15: Microsoft Endpoint Manager | AD15: 90 | AE15: Compliant | AF15: Missing environment
A16: 8b7e2ec5609f4e96b9a2b9e099aca3fd | B16: PC-0100007 | C16: cmdb_ci_pc_hardware | D16: AST-11707806 | E16: SN9837508065 | F16: Dell | G16: OptiPlex 7090 | J16: Installed | K16: Operational | L16: 10.26.206.175 | O16: 8 | P16: 8 | Q16: 256 | R16: Anjali Kumar | S16: Desktop Support | U16: Ravi Patel | V16: Lakshmi Nair | W16: 2023-05-24 11:09:17 | X16: 2026-05-23 11:09:17 | Y16: Service Mapping | Z16: Microsoft 365 | AA16: Enterprise Email | AB16: Power Platform | AC16: Microsoft Endpoint Manager | AD16: 70 | AE16: Partially Compliant | AF16: Missing environment; Missing support_group; Missing location
A17: 516979c75f794a0dab6be89a1ed51f8a | B17: vm-prd-new-00003 | C17: cmdb_ci_vmware_instance | D17: AST-54598574 | E17: SN5025509840 | F17: VMware | G17: vSphere VM | H17: New York-DC | I17: Production | J17: Installed | K17: Operational | L17: 10.50.83.89 | M17: Red Hat Enterprise Linux | N17: 9.2 | O17: 4 | P17: 64 | Q17: 200 | S17: Cloud Operations | T17: Cloud Operations | U17: Vikram Shetty | V17: Rajesh Nair | W17: 2025-11-19 11:09:17 | X17: 2026-05-07 11:09:17 | Y17: ServiceNow Discovery | Z17: SAP ERP | AA17: Record-to-Report | AB17: SAP S/4HANA Procurement | AC17: SAP HANA Database | AD17: 100 | AE17: Compliant | AF17: None
A18: 538f73c331434f59a11254da1b246e5a | B18: PC-0100008 | C18: cmdb_ci_pc_hardware | D18: AST-29191841 | E18: SN3518001184 | F18: Dell | G18: OptiPlex 7090 | I18: Production | J18: Installed | K18: Operational | L18: 10.18.10.204 | O18: 6 | P18: 16 | Q18: 1000 | R18: Sarah Joshi | S18: End User Computing | T18: End User Computing | U18: Manish Rao | V18: James Joshi | W18: 2025-01-26 11:09:17 | X18: 2026-05-21 11:09:17 | Y18: SCCM | Z18: Microsoft 365 | AA18: Video Conferencing | AB18: OneDrive for Business | AC18: M365 Defender | AD18: 90 | AE18: Compliant | AF18: Missing location
A19: 0ded17b1c8b34b2b837d6bd66a2ecbf7 | B19: vm-pre-mum-00004 | C19: cmdb_ci_vmware_instance | D19: AST-97696385 | E19: SN7550580157 | F19: VMware | G19: vSphere VM | H19: Mumbai-DC1 | I19: Pre-Production | K19: Operational | L19: 10.196.40.177 | M19: Red Hat Enterprise Linux | N19: 8.6 | O19: 64 | P19: 16 | Q19: 500 | S19: Virtualization Team | T19: Virtualization Team | U19: Ravi Mehta | V19: Rajesh Krishnan | W19: 2022-09-24 11:09:17 | X19: 2026-04-29 11:09:17 | Y19: ServiceNow Discovery | Z19: Adobe | AA19: Content Authoring | AB19: Adobe Workfront | AC19: Adobe Asset Service | AD19: 90 | AE19: Compliant | AF19: Missing install_status
A20: 4e0101d93e5e4674ac371373f7c61d1e | B20: PC-0100009 | C20: cmdb_ci_pc_hardware | D20: AST-32365378 | E20: SN8880139493 | F20: Dell | G20: Latitude 5540 | H20: New York-DC | I20: Production | J20: Installed | K20: DR Standby | L20: 10.36.1.3 | O20: 6 | P20: 32 | Q20: 256 | R20: David Kumar | S20: End User Computing | T20: End User Computing | U20: James Patel | V20: Robert Desai | W20: 2022-12-29 11:09:17 | X20: 2026-05-13 11:09:17 | Y20: ServiceNow Discovery | Z20: Microsoft 365 | AA20: File Storage & Sync | AB20: Power Platform | AC20: Microsoft Graph API | AD20: 100 | AE20: Compliant | AF20: None
A21: 7c99c7ab3c4a4024a57e7c27e2c139ac | B21: PC-0100010 | C21: cmdb_ci_pc_hardware | D21: AST-24833479 | E21: SN1142307138 | F21: HP | G21: EliteBook 840 G10 | H21: Hyderabad-DC1 | I21: Production | J21: Installed | K21: Operational | L21: 10.15.86.21 | O21: 4 | P21: 8 | Q21: 1000 | R21: Shreya Patel | S21: Desktop Support | T21: Desktop Support | U21: Pooja Sharma | V21: Anjali Rao | W21: 2024-08-15 11:09:17 | X21: 2026-02-17 11:09:17 | Y21: Manual | Z21: Adobe | AA21: Web Analytics | AB21: Adobe Experience Manager | AC21: Adobe Asset Service | AD21: 90 | AE21: Compliant | AF21: Stale discovery (>90 days)
A22: 5612efb59cc44728aa6e781781c8dafc | B22: PC-0100011 | C22: cmdb_ci_pc_hardware | D22: AST-40012723 | E22: SN1329010027 | F22: Dell | G22: Latitude 5540 | H22: London-DR | I22: UAT | J22: Installed | K22: Operational | L22: 10.198.23.104 | O22: 6 | P22: 32 | Q22: 1000 | R22: Neha Brown | S22: End User Computing | T22: End User Computing | U22: Anand Mehta | V22: Lakshmi Nair | W22: 2024-08-08 11:09:17 | X22: 2026-05-14 11:09:17 | Y22: Service Mapping | Z22: Adobe | AA22: Marketing Automation | AB22: Adobe Campaign | AC22: Adobe Cloud Storage | AD22: 100 | AE22: Compliant | AF22: None
A23: e10f9fae60594506810ef0a1244bb29b | B23: vm-prd-hyd-00005 | C23: cmdb_ci_vmware_instance | D23: AST-64183558 | E23: SN6985738789 | F23: VMware | G23: vSphere VM | H23: Hyderabad-DC1 | I23: Production | J23: Installed | K23: Operational | L23: 10.25.199.201 | M23: Windows Server | N23: 2022 Datacenter | O23: 8 | P23: 256 | Q23: 8000 | S23: Virtualization Team | T23: Virtualization Team | U23: Kavita Sharma | V23: Anjali Banerjee | W23: 2024-12-03 11:09:17 | X23: 2026-05-03 11:09:17 | Y23: ServiceNow Discovery | Z23: Workday | AA23: Time & Attendance | AB23: Workday Payroll Engine | AC23: Identity Federation (SAML) | AD23: 100 | AE23: Compliant | AF23: None
A24: 430311f46cba4039a9b4208666d4db85 | B24: vm-prd-lon-00006 | C24: cmdb_ci_vmware_instance | D24: AST-26230649 | E24: SN8386614925 | F24: VMware | G24: vSphere VM | H24: London-DR | I24: Production | J24: Installed | K24: Operational | L24: 10.39.35.27 | M24: Windows Server | N24: 2019 Standard | O24: 24 | P24: 768 | Q24: 4000 | S24: Cloud Operations | T24: Cloud Operations | U24: Aditya Pillai | V24: Michael Banerjee | W24: 2023-02-22 11:09:17 | X24: 2026-05-15 11:09:17 | Y24: CSV Import | Z24: Adobe | AA24: Digital Asset Management | AB24: Adobe Analytics | AC24: Adobe Cloud Storage | AD24: 100 | AE24: Compliant | AF24: None
A25: d2c07f52c58546c4bb9ca258fb152cc4 | B25: vm-prd-new-00007 | C25: cmdb_ci_vmware_instance | D25: AST-67600146 | E25: SN4581183735 | F25: VMware | G25: vSphere VM | H25: New York-DC | I25: Production | J25: Installed | K25: Operational | L25: 10.47.199.193 | M25: Windows Server | N25: 2019 Standard | O25: 24 | P25: 64 | Q25: 8000 | S25: Cloud Operations | T25: Cloud Operations | U25: Arjun Wilson | V25: Ravi Taylor | W25: 2022-10-07 11:09:17 | X25: 2025-09-18 11:09:17 | Y25: ServiceNow Discovery | Z25: Oracle Fusion ERP | AA25: Risk & Compliance | AB25: Oracle Fusion Project Mgmt | AC25: Oracle Analytics Cloud | AD25: 90 | AE25: Compliant | AF25: Stale discovery (>90 days)
A26: 23893d5faf3e40518390de8216407f11 | B26: PC-0100012 | C26: cmdb_ci_pc_hardware | D26: AST-63902681 | E26: SN6272873906 | F26: Dell | G26: Latitude 5540 | H26: Mumbai-DC1 | I26: Pre-Production | J26: Installed | K26: Operational | L26: 10.89.253.65 | O26: 8 | P26: 32 | Q26: 512 | R26: Sunita Kumar | S26: Desktop Support | T26: Desktop Support | U26: Michael Rao | V26: Kavita Verma | W26: 2024-08-10 11:09:17 | X26: 2026-05-13 11:09:17 | Y26: SCCM | Z26: SAP ERP | AA26: Order-to-Cash | AB26: SAP S/4HANA Sales | AC26: SAP Solution Manager | AD26: 100 | AE26: Compliant | AF26: None
A27: 287566a05ab3459e8bfa5cede81b9121 | B27: lnx-dev-che-00002 | C27: cmdb_ci_linux_server | D27: AST-75458523 | E27: SN9642064576 | F27: HPE | G27: ProLiant DL380 Gen10 | I27: Development | J27: Installed | K27: Operational | L27: 10.191.122.90 | M27: Oracle Linux | N27: 8.7 | O27: 96 | P27: 384 | Q27: 500 | S27: Platform Engineering | U27: Anand Krishnan | V27: Aditya Sharma | W27: 2023-04-23 11:09:17 | X27: 2026-05-16 11:09:17 | Y27: Service Mapping | Z27: SAP ERP | AA27: Procure-to-Pay | AB27: SAP Fiori Launchpad | AC27: SAP Gateway OData Service | AD27: 80 | AE27: Compliant | AF27: Missing location; Missing support_group
A28: 4159763d15c94884af0990b1d0cbde10 | B28: lnx-prd-mum-00003 | C28: cmdb_ci_linux_server | D28: AST-42851197 | E28: SN7393676837 | F28: Dell EMC | I28: Production | J28: In Maintenance | L28: 10.35.128.58 | M28: Red Hat Enterprise Linux | N28: 9.2 | O28: 16 | P28: 128 | Q28: 16000 | S28: Unix Operations | T28: Unix Operations | V28: Arjun Brown | W28: 2022-04-25 11:09:17 | X28: 2026-05-22 11:09:17 | Y28: Service Mapping | Z28: Oracle Fusion ERP | AA28: Treasury Operations | AB28: Oracle Fusion Tax Reporting | AC28: Oracle Identity Cloud Service | AD28: 60 | AE28: Partially Compliant | AF28: Missing owned_by; Missing model_id; Missing operational_status; Missing location
A29: c1d4cce401df42019c6bd7695cd6783d | B29: win-pre-hyd-00002 | C29: cmdb_ci_win_server | D29: AST-71686158 | E29: SN8061808780 | F29: HPE | H29: Hyderabad-DC1 | I29: Pre-Production | J29: In Maintenance | K29: Operational | L29: 10.139.75.236 | M29: Windows Server | N29: 2022 Datacenter | O29: 64 | P29: 64 | Q29: 2000 | S29: Platform Engineering | T29: Platform Engineering | V29: Anand Taylor | W29: 2025-07-05 11:09:17 | X29: 2026-05-19 11:09:17 | Y29: ServiceNow Discovery | Z29: SAP ERP | AA29: Inventory & Warehouse | AB29: SAP S/4HANA Finance | AC29: SAP NetWeaver Application Server | AD29: 80 | AE29: Compliant | AF29: Missing owned_by; Missing model_id
A30: 4013c7b20e3a4404907016e86603339e | B30: app-uat-sin-00003 | C30: cmdb_ci_app_server | D30: AST-77269965 | F30: Apache Foundation | G30: Tomcat 10 | H30: Singapore-DC | I30: UAT | K30: DR Standby | L30: 10.164.38.220 | O30: 32 | P30: 32 | Q30: 500 | S30: Java Platform Team | T30: Java Platform Team | U30: Rajesh Iyer | V30: Lisa Banerjee | W30: 2024-07-08 11:09:17 | X30: 2026-05-15 11:09:17 | Y30: Service Mapping | Z30: Oracle Fusion ERP | AA30: Project Portfolio Mgmt | AB30: Oracle Fusion Financials | AC30: Oracle Analytics Cloud | AD30: 80 | AE30: Compliant | AF30: Missing serial_number; Missing install_status
A31: 4478f9f9288643eb834805d315940dca | B31: PC-0100013 | C31: cmdb_ci_pc_hardware | D31: AST-46254895 | E31: SN8581434181 | F31: Apple | G31: MacBook Pro 14" | H31: New York-DC | I31: Production | J31: Installed | K31: Operational | L31: 10.12.209.146 | O31: 6 | P31: 16 | Q31: 1000 | R31: Michael Verma | S31: End User Computing | T31: End User Computing | U31: Lisa Krishnan | V31: Michael Rao | W31: 2023-09-30 11:09:17 | X31: 2026-05-23 11:09:17 | Y31: SCCM | Z31: Microsoft 365 | AA31: Video Conferencing | AB31: Power Platform | AC31: M365 Defender | AD31: 100 | AE31: Compliant | AF31: None
A32: 0556068ef88548b49a028a9fa9d18a5e | B32: lnx-uat-hyd-00004 | C32: cmdb_ci_linux_server | D32: AST-57630460 | E32: SN7862013536 | F32: HPE | G32: ProLiant DL360 Gen10 | H32: Hyderabad-DC1 | I32: UAT | J32: Installed | K32: DR Standby | L32: 10.80.236.243 | M32: Red Hat Enterprise Linux | N32: 9.2 | O32: 64 | P32: 384 | Q32: 16000 | S32: Unix Operations | T32: Unix Operations | V32: Anjali Jones | W32: 2024-03-28 11:09:17 | X32: 2026-05-07 11:09:17 | Y32: SCCM | Z32: Microsoft 365 | AA32: Video Conferencing | AB32: OneDrive for Business | AC32: Exchange Transport Service | AD32: 90 | AE32: Compliant | AF32: Missing owned_by
A33: 6716024727d84647bb4250776a076624 | B33: PC-0100014 | C33: cmdb_ci_pc_hardware | D33: AST-27615610 | E33: SN2370504045 | G33: Latitude 5540 | J33: Installed | K33: Operational | L33: 10.33.67.13 | O33: 8 | P33: 32 | Q33: 512 | R33: Pooja Krishnan | S33: Desktop Support | U33: Suresh Jones | V33: Suresh Williams | W33: 2022-04-24 11:09:17 | X33: 2026-05-14 11:09:17 | Y33: SCCM | Z33: Microsoft 365 | AA33: Internal Communications | AB33: Microsoft Purview | AC33: Microsoft Endpoint Manager | AD33: 60 | AE33: Partially Compliant | AF33: Missing manufacturer; Missing support_group; Missing location; Missing environment
A34: 283102dea02c413daf5a686e611824e1 | B34: PC-0100015 | C34: cmdb_ci_pc_hardware | D34: AST-72241165 | E34: SN9801437687 | G34: ThinkPad X1 Carbon | H34: Gurgaon-Office | I34: Production | L34: 10.27.78.199 | O34: 4 | P34: 8 | Q34: 256 | R34: Ravi Nair | S34: IT Service Desk | U34: Rajesh Singh | V34: David Nair | W34: 2023-08-02 11:09:17 | X34: 2024-12-19 11:09:17 | Y34: CSV Import | Z34: Microsoft 365 | AA34: Document Collaboration | AB34: Microsoft Teams | AC34: Exchange Transport Service | AD34: 50 | AE34: Non-Compliant | AF34: Missing operational_status; Missing install_status; Missing support_group; Missing manufacturer; Stale discovery (>90 days)
A35: 98e963bae5c84664803608c7c5ec46d9 | B35: lnx-dr-lon-00005 | C35: cmdb_ci_linux_server | D35: AST-32631985 | E35: SN9943858941 | H35: London-DR | I35: DR | J35: Installed | K35: Operational | L35: 10.197.23.109 | M35: Oracle Linux | N35: 8.7 | O35: 96 | P35: 768 | Q35: 2000 | S35: Platform Engineering | V35: Suresh Jones | W35: 2024-06-26 11:09:17 | X35: 2026-05-06 11:09:17 | Y35: Manual | Z35: Adobe | AA35: Digital Asset Management | AB35: Adobe Analytics | AC35: Adobe Cloud Storage | AD35: 60 | AE35: Partially Compliant | AF35: Missing manufacturer; Missing owned_by; Missing model_id; Missing support_group
A36: 9f659268a1924bce90c16f37a8c72388 | B36: AppSvc-0001 | C36: cmdb_ci_service_auto | D36: AST-10469596 | E36: SN4621129671 | F36: Internal | G36: Application Service | I36: DR | K36: Operational | S36: Application Support L2 | U36: Priya Sharma | V36: Mary Nair | W36: 2026-02-23 11:09:17 | X36: 2026-04-29 11:09:17 | Y36: ServiceNow Discovery | Z36: Microsoft 365 | AA36: Document Collaboration | AB36: OneDrive for Business | AC36: Exchange Transport Service | AD36: 70 | AE36: Partially Compliant | AF36: Missing location; Missing install_status; Missing support_group
A37: 228acb3610984eecabc01032384e04a8 | B37: win-tst-mum-00003 | C37: cmdb_ci_win_server | D37: AST-44687867 | E37: SN9635493133 | H37: Mumbai-DC2 | I37: Test | J37: Installed | K37: Operational | L37: 10.112.13.132 | M37: Windows Server | N37: 2022 Datacenter | O37: 16 | P37: 64 | Q37: 500 | S37: Windows Admins | T37: Windows Admins | U37: Anjali Patel | V37: Sunita Shetty | W37: 2025-06-01 11:09:17 | X37: 2026-05-14 11:09:17 | Y37: Service Mapping | Z37: SAP ERP | AA37: Record-to-Report | AB37: SAP Fiori Launchpad | AC37: SAP Gateway OData Service | AD37: 80 | AE37: Compliant | AF37: Missing model_id; Missing manufacturer
A38: 3bdd9a76d10849e1b201e8ea20804e74 | B38: PC-0100016 | C38: cmdb_ci_pc_hardware | D38: AST-42072501 | E38: SN4700789281 | F38: Lenovo | I38: Production | J38: Installed | L38: 10.41.11.77 | O38: 8 | P38: 32 | Q38: 512 | R38: James Krishnan | S38: End User Computing | T38: End User Computing | V38: Anand Banerjee | W38: 2023-01-04 11:09:17 | X38: 2026-05-15 11:09:17 | Y38: SCCM | Z38: Adobe | AA38: Digital Asset Management | AB38: Adobe Campaign | AC38: Adobe API Gateway | AD38: 60 | AE38: Partially Compliant | AF38: Missing owned_by; Missing model_id; Missing location; Missing operational_status
A39: 20beae7b97af45d1ae930d1150eb9f37 | B39: win-prd-ben-00004 | C39: cmdb_ci_win_server | D39: AST-21580293 | E39: SN1017288429 | F39: Lenovo | G39: ThinkSystem SR650 | H39: Bengaluru-DC1 | I39: Production | J39: Installed | K39: Operational | L39: 10.35.97.78 | M39: Windows Server | N39: 2022 Standard | O39: 4 | P39: 768 | Q39: 1000 | S39: Wintel Operations | T39: Wintel Operations | U39: Anjali Sharma | V39: Neha Mehta | W39: 2024-02-15 11:09:17 | X39: 2026-05-20 11:09:17 | Y39: ServiceNow Discovery | Z39: Oracle Fusion ERP | AA39: Project Portfolio Mgmt | AB39: Oracle Fusion Risk Mgmt | AC39: Oracle Integration Cloud | AD39: 100 | AE39: Compliant | AF39: None
A40: 5b3c9686e27b45d6835b60c2669163a2 | B40: db-dev-che-00001 | C40: cmdb_ci_db_instance | D40: AST-31801691 | E40: SN7388882254 | F40: Microsoft | G40: SQL Server 2019 | H40: Chennai-DC1 | I40: Development | J40: Installed | K40: Operational | L40: 10.179.198.35 | O40: 64 | P40: 32 | Q40: 4000 | S40: DBA - PostgreSQL | T40: DBA - PostgreSQL | U40: Vikram Patel | V40: Aditya Brown | W40: 2024-02-29 11:09:17 | X40: 2026-05-22 11:09:17 | Y40: ServiceNow Discovery | Z40: SAP ERP | AA40: Order-to-Cash | AB40: SAP S/4HANA Production | AC40: SAP NetWeaver Application Server | AD40: 100 | AE40: Compliant | AF40: None
A41: 5e665cad3af44c16a1ca18ab6595bbfe | B41: lnx-prd-hyd-00006 | C41: cmdb_ci_linux_server | E41: SN1174030030 | G41: ProLiant DL380 Gen10 | H41: Hyderabad-DC1 | I41: Production | K41: Operational | L41: 10.25.124.218 | M41: Red Hat Enterprise Linux | N41: 9.2 | O41: 8 | P41: 768 | Q41: 200 | S41: Linux Admins | T41: Linux Admins | V41: Michael Nair | W41: 2024-03-18 11:09:17 | X41: 2026-05-05 11:09:17 | Y41: Manual | Z41: Oracle Fusion ERP | AA41: Treasury Operations | AB41: Oracle Fusion Tax Reporting | AC41: Oracle Identity Cloud Service | AD41: 60 | AE41: Partially Compliant | AF41: Missing manufacturer; Missing asset_tag; Missing install_status; Missing owned_by
A42: 308634360b9f45368b06c9b315946596 | B42: win-prd-lon-00005 | C42: cmdb_ci_win_server | D42: AST-62998477 | E42: SN4616529033 | F42: HPE | G42: ProLiant DL580 Gen10 | H42: London-DR | I42: Production | J42: Retired | K42: Operational | L42: 10.24.241.209 | M42: Windows Server | N42: 2019 Standard | O42: 4 | P42: 32 | Q42: 16000 | S42: Wintel Operations | T42: Wintel Operations | U42: Deepika Reddy | V42: Arjun Williams | W42: 2022-04-27 11:09:17 | X42: 2026-05-14 11:09:17 | Y42: CSV Import | Z42: Oracle Fusion ERP | AA42: Treasury Operations | AB42: Oracle Fusion Financials | AC42: Oracle Analytics Cloud | AD42: 100 | AE42: Compliant | AF42: None
A43: 722fcab9ec364159bf63169a026dda4e | B43: PC-0100017 | C43: cmdb_ci_pc_hardware | D43: AST-39520915 | E43: SN8859609410 | F43: Lenovo | G43: ThinkPad T14 | H43: Mumbai-DC2 | I43: Pre-Production | J43: Installed | K43: Operational | L43: 10.166.186.209 | O43: 8 | P43: 16 | Q43: 1000 | R43: Lisa Jones | S43: IT Service Desk | U43: Sunita Krishnan | V43: Aditya Rao | W43: 2024-11-21 11:09:17 | X43: 2026-05-07 11:09:17 | Y43: Service Mapping | Z43: Adobe | AA43: Digital Asset Management | AB43: Adobe Analytics | AC43: Adobe Cloud Storage | AD43: 90 | AE43: Compliant | AF43: Missing support_group
A44: 814d9899340c45cba02c57713c1fd434 | B44: web-prd-pun-00001 | C44: cmdb_ci_web_server | D44: AST-68366156 | E44: SN2383810331 | F44: F5 | G44: BIG-IP 17.1 | H44: Pune-Office | I44: Production | J44: Installed | L44: 10.10.209.28 | O44: 48 | P44: 384 | Q44: 200 | S44: Web Operations | U44: Emma Singh | V44: Manish Rao | W44: 2024-07-25 11:09:17 | X44: 2026-05-21 11:09:17 | Y44: CSV Import | Z44: Workday | AA44: HR Self-Service | AB44: Workday Time Tracking | AC44: Workday Reporting Service | AD44: 80 | AE44: Compliant | AF44: Missing support_group; Missing operational_status
A45: a4660f54860c453faf7614ab9bd2c824 | B45: PC-0100018 | C45: cmdb_ci_pc_hardware | D45: AST-90535130 | E45: SN5045091530 | F45: Lenovo | G45: ThinkPad X1 Carbon | H45: Bengaluru-DC2 | J45: Installed | L45: 10.69.250.109 | O45: 8 | P45: 16 | Q45: 512 | R45: Neha Sharma | S45: IT Service Desk | U45: John Reddy | V45: Meera Reddy | W45: 2026-01-31 11:09:17 | X45: 2026-05-03 11:09:17 | Y45: Service Mapping | Z45: Workday | AA45: Talent Acquisition | AB45: Workday Recruiting Portal | AC45: HR Data Integration Bus | AD45: 70 | AE45: Partially Compliant | AF45: Missing operational_status; Missing environment; Missing support_group
A46: b125b8650ddf4256a5b66b35bcb8161e | B46: PC-0100019 | C46: cmdb_ci_pc_hardware | D46: AST-63926843 | E46: SN8110568314 | F46: Dell | G46: OptiPlex 7090 | H46: Mumbai-DC1 | I46: Production | J46: Installed | K46: Operational | L46: 10.41.66.96 | O46: 8 | P46: 32 | Q46: 256 | R46: Priya Taylor | S46: End User Computing | T46: End User Computing | U46: David Rao | V46: Anjali Nair | W46: 2026-03-27 11:09:17 | X46: 2026-05-05 11:09:17 | Y46: SCCM | Z46: Microsoft 365 | AA46: Video Conferencing | AB46: Microsoft Purview | AC46: Microsoft Graph API | AD46: 100 | AE46: Compliant | AF46: None
A47: 69b2a9077bf248c8a32d669afa7cbd7f | B47: vm-dev-ben-00008 | C47: cmdb_ci_vmware_instance | D47: AST-12114732 | E47: SN1994012762 | G47: vSphere VM | H47: Bengaluru-DC2 | I47: Development | K47: Operational | L47: 10.77.94.33 | M47: Windows Server | N47: 2019 Datacenter | O47: 48 | P47: 128 | Q47: 16000 | S47: Virtualization Team | T47: Virtualization Team | U47: Robert Patel | V47: Vikram Singh | W47: 2025-08-01 11:09:17 | X47: 2026-05-05 11:09:17 | Y47: SCCM | Z47: SAP ERP | AA47: Inventory & Warehouse | AB47: SAP S/4HANA Procurement | AC47: SAP HANA Database | AD47: 80 | AE47: Compliant | AF47: Missing install_status; Missing manufacturer
A48: aff52aa4129e4daca24e8c4d3f79aea4 | B48: vm-prd-che-00009 | C48: cmdb_ci_vmware_instance | D48: AST-22960956 | E48: SN2081234251 | F48: VMware | I48: Production | K48: Operational | L48: 10.16.118.72 | M48: Windows Server | N48: 2022 Datacenter | O48: 48 | P48: 128 | Q48: 200 | S48: Virtualization Team | T48: Virtualization Team | V48: Meera Kumar | W48: 2022-09-25 11:09:17 | X48: 2026-05-02 11:09:17 | Y48: ServiceNow Discovery | Z48: Oracle Fusion ERP | AA48: Risk & Compliance | AB48: Oracle Fusion Tax Reporting | AC48: Oracle Analytics Cloud | AD48: 60 | AE48: Partially Compliant | AF48: Missing model_id; Missing owned_by; Missing install_status; Missing location
A49: f3cd141dc44941d8b0e6c53dceb28760 | B49: sw-pre-pun-00003 | C49: cmdb_ci_ip_switch | D49: AST-32279169 | E49: SN7298968423 | F49: Cisco | G49: Nexus 9336C-FX2 | H49: Pune-Office | I49: Pre-Production | J49: Installed | K49: Operational | L49: 10.123.60.119 | S49: Network Engineering | T49: Network Engineering | U49: Lakshmi Smith | V49: Lisa Smith | W49: 2025-03-23 11:09:17 | X49: 2026-05-05 11:09:17 | Y49: Service Mapping | Z49: Workday | AA49: Time & Attendance | AB49: Workday Benefits Admin | AC49: Workday Reporting Service | AD49: 100 | AE49: Compliant | AF49: None
A50: 097b6a8df4bd40c68df37485e4e81ed8 | B50: win-pre-pun-00006 | C50: cmdb_ci_win_server | D50: AST-43777512 | F50: HPE | H50: Pune-Office | J50: Installed | K50: Operational | L50: 10.63.222.172 | M50: Windows Server | N50: 2019 Standard | O50: 48 | P50: 128 | Q50: 16000 | S50: Platform Engineering | U50: Lakshmi Williams | V50: Meera Reddy | W50: 2023-09-05 11:09:17 | X50: 2026-05-05 11:09:17 | Y50: Service Mapping | Z50: Workday | AA50: HR Self-Service | AB50: Workday Recruiting Portal | AC50: Identity Federation (SAML) | AD50: 60 | AE50: Partially Compliant | AF50: Missing serial_number; Missing model_id; Missing support_group; Missing environment
A51: 8d0da2a7fb084c1083b8443fd35ef14d | B51: PC-0100020 | C51: cmdb_ci_pc_hardware | D51: AST-47103983 | E51: SN4547529911 | F51: HP | G51: EliteBook 840 G10 | H51: Pune-Office | I51: Production | J51: Installed | K51: Operational | L51: 10.34.159.93 | O51: 8 | P51: 16 | Q51: 512 | R51: Pooja Pillai | S51: Desktop Support | T51: Desktop Support | U51: Arjun Krishnan | V51: Anand Jones | W51: 2024-03-22 11:09:17 | X51: 2026-05-09 11:09:17 | Y51: CSV Import | Z51: Microsoft 365 | AA51: Enterprise Email | AB51: SharePoint Online | AC51: Exchange Transport Service | AD51: 100 | AE51: Compliant | AF51: None
A52: 207bd478ec744ed2a775149a741f2fd7 | B52: PC-0100021 | C52: cmdb_ci_pc_hardware | D52: AST-84007063 | E52: SN2251136052 | F52: HP | G52: EliteBook 840 G10 | I52: DR | J52: Installed | K52: Operational | L52: 10.132.35.45 | O52: 8 | P52: 32 | Q52: 1000 | R52: James Krishnan | S52: IT Service Desk | T52: IT Service Desk | U52: John Kumar | V52: Aditya Verma | W52: 2023-08-18 11:09:17 | X52: 2026-04-29 11:09:17 | Y52: SCCM | Z52: Microsoft 365 | AA52: Document Collaboration | AB52: Microsoft Purview | AC52: Microsoft Endpoint Manager | AD52: 90 | AE52: Compliant | AF52: Missing location
A53: d9ad0c447fd943fda4b10119195479cf | B53: AppSvc-0002 | C53: cmdb_ci_service_auto | D53: AST-99503644 | E53: SN9247501998 | F53: Internal | G53: Application Service | H53: Chennai-DC1 | I53: Development | J53: Installed | K53: Operational | S53: Service Owners | T53: Service Owners | U53: Ravi Patel | V53: Pooja Taylor | W53: 2022-06-17 11:09:17 | X53: 2026-05-06 11:09:17 | Y53: BMC ADDM | Z53: Workday | AA53: HR Self-Service | AB53: Workday Benefits Admin | AC53: Workday Reporting Service | AD53: 100 | AE53: Compliant | AF53: None
A54: db7eb333697f48b8929a488d413f9c6c | B54: lnx-dr-gur-00007 | C54: cmdb_ci_linux_server | D54: AST-46028268 | E54: SN8740481631 | F54: Cisco | G54: UCS C220 M6 | H54: Gurgaon-Office | I54: DR | J54: Installed | K54: DR Standby | L54: 10.180.133.211 | M54: Red Hat Enterprise Linux | N54: 8.6 | O54: 24 | P54: 128 | Q54: 500 | S54: Linux Admins | T54: Linux Admins | U54: James Singh | V54: Kavita Kumar | W54: 2024-02-03 11:09:17 | X54: 2026-05-07 11:09:17 | Y54: ServiceNow Discovery | Z54: Workday | AA54: Payroll Processing | AB54: Workday Time Tracking | AC54: Identity Federation (SAML) | AD54: 100 | AE54: Compliant | AF54: None
A55: d52123b951be452eaabfa079a6ce8d2e | B55: PC-0100022 | C55: cmdb_ci_pc_hardware | D55: AST-84394179 | E55: SN3274111660 | F55: HP | G55: EliteBook 840 G10 | H55: Bengaluru-DC2 | I55: Test | J55: Installed | K55: Operational | L55: 10.121.148.62 | O55: 8 | P55: 16 | Q55: 1000 | R55: Suresh Wilson | S55: IT Service Desk | T55: IT Service Desk | U55: Michael Rao | V55: Michael Brown | W55: 2024-09-20 11:09:17 | X55: 2026-05-14 11:09:17 | Y55: Service Mapping | Z55: Microsoft 365 | AA55: Enterprise Email | AB55: Exchange Online | AC55: Exchange Transport Service | AD55: 100 | AE55: Compliant | AF55: None
A56: b14720f6d18643ff86ca05d18da693b1 | B56: PC-0100023 | C56: cmdb_ci_pc_hardware | D56: AST-96650561 | E56: SN8923314250 | F56: Dell | G56: Latitude 5540 | H56: Gurgaon-Office | K56: Operational | L56: 10.168.111.30 | O56: 8 | P56: 32 | Q56: 256 | R56: Rajesh Nair | S56: Desktop Support | T56: Desktop Support | U56: Vikram Verma | V56: Anand Shetty | W56: 2022-08-20 11:09:17 | X56: 2025-01-23 11:09:17 | Y56: Manual | Z56: Microsoft 365 | AA56: Document Collaboration | AB56: Power Platform | AC56: Microsoft Endpoint Manager | AD56: 70 | AE56: Partially Compliant | AF56: Missing environment; Missing install_status; Stale discovery (>90 days)
A57: 56b2f57607c1468ba4427a6d0d65ecb5 | B57: sw-dr-mum-00004 | C57: cmdb_ci_ip_switch | D57: AST-60263635 | E57: SN6135814985 | G57: 7050X3-48YC | H57: Mumbai-DC2 | I57: DR | J57: Installed | L57: 10.176.137.163 | S57: Network Operations | T57: Network Operations | U57: Vikram Shetty | V57: Suresh Williams | W57: 2024-08-21 11:09:17 | X57: 2026-05-10 11:09:17 | Y57: Manual | Z57: Oracle Fusion ERP | AA57: Treasury Operations | AB57: Oracle Fusion Tax Reporting | AC57: Oracle REST Data Service | AD57: 80 | AE57: Compliant | AF57: Missing manufacturer; Missing operational_status
A58: 090877d22c8a4d05bf96e8c2b352545f | B58: PC-0100024 | C58: cmdb_ci_pc_hardware | E58: SN8446962054 | F58: HP | G58: EliteBook 840 G10 | I58: Production | J58: Installed | K58: Operational | L58: 10.23.197.203 | O58: 8 | P58: 32 | Q58: 256 | R58: Emma Desai | S58: Desktop Support | V58: Meera Brown | W58: 2025-10-13 11:09:17 | X58: 2026-05-05 11:09:17 | Y58: BMC ADDM | Z58: Adobe | AA58: Digital Asset Management | AB58: Adobe Analytics | AC58: Adobe Cloud Storage | AD58: 60 | AE58: Partially Compliant | AF58: Missing support_group; Missing location; Missing owned_by; Missing asset_tag
A59: fef29a47874243a594891f91650f1066 | B59: web-prd-sin-00002 | C59: cmdb_ci_web_server | D59: AST-79676468 | E59: SN6626415130 | F59: Apache Foundation | G59: Apache HTTPD 2.4 | H59: Singapore-DC | I59: Production | J59: Installed | K59: Operational | L59: 10.25.131.193 | O59: 32 | P59: 64 | Q59: 4000 | S59: Middleware Admins | T59: Middleware Admins | U59: Vikram Kumar | V59: Meera Krishnan | W59: 2025-09-09 11:09:17 | X59: 2026-05-01 11:09:17 | Y59: SCCM | Z59: Microsoft 365 | AA59: Internal Communications | AB59: OneDrive for Business | AC59: Microsoft Endpoint Manager | AD59: 100 | AE59: Compliant | AF59: None
A60: dcd6f686f3e74f6ba00f4ad17d08a092 | B60: lnx-prd-sin-00008 | C60: cmdb_ci_linux_server | D60: AST-23143868 | E60: SN8507140070 | F60: Lenovo | G60: ThinkSystem SR650 | H60: Singapore-DC | I60: Production | J60: Installed | K60: Operational | L60: 10.28.5.99 | M60: Red Hat Enterprise Linux | N60: 8.6 | O60: 4 | P60: 384 | Q60: 16000 | S60: Linux Admins | T60: Linux Admins | U60: James Williams | V60: David Reddy | W60: 2025-01-28 11:09:17 | X60: 2026-05-06 11:09:17 | Y60: SCCM | Z60: SAP ERP | AA60: Production Planning | AB60: SAP S/4HANA Logistics | AC60: SAP Solution Manager | AD60: 100 | AE60: Compliant | AF60: None
A61: 8959afbfdff44d64a16bf203cb23aeb8 | B61: PC-0100025 | C61: cmdb_ci_pc_hardware | E61: SN9087219220 | G61: EliteBook 840 G10 | H61: Gurgaon-Office | I61: Production | J61: Installed | K61: DR Standby | L61: 10.29.193.14 | O61: 4 | P61: 8 | Q61: 512 | R61: Pooja Reddy | S61: End User Computing | V61: Meera Sharma | W61: 2023-01-04 11:09:17 | X61: 2026-05-13 11:09:17 | Y61: SCCM | Z61: Microsoft 365 | AA61: Enterprise Email | AB61: OneDrive for Business | AC61: Entra ID (Azure AD) | AD61: 60 | AE61: Partially Compliant | AF61: Missing owned_by; Missing manufacturer; Missing support_group; Missing asset_tag
A62: 106858895792458299c76b39b6837298 | B62: win-prd-dub-00007 | C62: cmdb_ci_win_server | D62: AST-62475326 | E62: SN8267052551 | F62: Lenovo | G62: ThinkSystem SR650 | H62: Dubai-DC | I62: Production | J62: Installed | K62: Operational | L62: 10.44.166.45 | M62: Windows Server | N62: 2022 Standard | O62: 24 | P62: 128 | Q62: 1000 | S62: Windows Admins | T62: Windows Admins | U62: Arjun Jones | V62: Neha Reddy | W62: 2023-10-05 11:09:17 | X62: 2026-05-13 11:09:17 | Y62: CSV Import | Z62: Oracle Fusion ERP | AA62: Project Portfolio Mgmt | AB62: Oracle Fusion Risk Mgmt | AC62: Oracle Autonomous Database | AD62: 100 | AE62: Compliant | AF62: None
A63: 3ac043b23434454dbf8dda7675ddd134 | B63: vm-prd-dub-00010 | C63: cmdb_ci_vmware_instance | D63: AST-88166629 | E63: SN7368652664 | F63: VMware | G63: vSphere VM | H63: Dubai-DC | I63: Production | J63: Installed | K63: Non-Operational | L63: 10.22.149.49 | M63: Ubuntu | N63: 20.04 LTS | O63: 8 | P63: 32 | Q63: 200 | S63: Cloud Operations | T63: Cloud Operations | U63: James Desai | V63: Rohit Verma | W63: 2022-08-12 11:09:17 | X63: 2026-05-12 11:09:17 | Y63: Manual | Z63: Oracle Fusion ERP | AA63: Financial Close | AB63: Oracle Fusion Procurement | AC63: Oracle Integration Cloud | AD63: 100 | AE63: Compliant | AF63: None
A64: 365aaf4355734e8ba61059f9059fb65d | B64: lnx-tst-mum-00009 | C64: cmdb_ci_linux_server | D64: AST-21986978 | E64: SN6822633009 | F64: Dell EMC | G64: PowerEdge R750 | H64: Mumbai-DC1 | I64: Test | J64: Installed | K64: Operational | L64: 10.159.126.109 | M64: Ubuntu | N64: 20.04 LTS | O64: 64 | P64: 32 | Q64: 4000 | S64: Unix Operations | T64: Unix Operations | U64: Ravi Wilson | V64: Lakshmi Smith | W64: 2024-07-08 11:09:17 | X64: 2025-03-06 11:09:17 | Y64: SCCM | Z64: SAP ERP | AA64: Record-to-Report | AB64: SAP S/4HANA Sales | AC64: SAP Gateway OData Service | AD64: 90 | AE64: Compliant | AF64: Stale discovery (>90 days)
A65: e871fb5a4fc54b29b75afdd642061d90 | B65: PC-0100026 | C65: cmdb_ci_pc_hardware | D65: AST-99885490 | E65: SN8243118290 | F65: HP | G65: EliteBook 840 G10 | H65: Mumbai-DC2 | I65: Production | J65: Installed | K65: Operational | L65: 10.29.121.181 | O65: 8 | P65: 8 | Q65: 256 | R65: Suresh Reddy | S65: End User Computing | T65: End User Computing | U65: Deepika Mehta | V65: Sarah Taylor | W65: 2025-10-03 11:09:17 | X65: 2026-05-08 11:09:17 | Y65: Manual | Z65: Adobe | AA65: Digital Asset Management | AB65: Adobe Workfront | AC65: Adobe API Gateway | AD65: 100 | AE65: Compliant | AF65: None
A66: fc5aa32ad16c41059842379cb8bbaef4 | B66: app-prd-che-00004 | C66: cmdb_ci_app_server | D66: AST-13360966 | E66: SN1927139121 | F66: Red Hat | G66: JBoss EAP 7.4 | H66: Chennai-DC1 | I66: Production | J66: Installed | K66: Operational | L66: 10.42.241.48 | O66: 32 | P66: 512 | Q66: 1000 | S66: Java Platform Team | T66: Java Platform Team | U66: Anjali Reddy | V66: Manish Patel | W66: 2025-03-18 11:09:17 | X66: 2026-04-29 11:09:17 | Y66: BMC ADDM | Z66: Oracle Fusion ERP | AA66: Project Portfolio Mgmt | AB66: Oracle Fusion Risk Mgmt | AC66: Oracle Autonomous Database | AD66: 100 | AE66: Compliant | AF66: None
A67: c7e6e91dd54a4a9184f1fc7fbac27d7c | B67: PC-0100027 | C67: cmdb_ci_pc_hardware | D67: AST-50355628 | E67: SN8341777356 | G67: ThinkPad T14 | H67: Dubai-DC | I67: Pre-Production | J67: Installed | K67: Operational | L67: 10.158.245.10 | O67: 8 | P67: 32 | Q67: 1000 | R67: Rohit Smith | S67: Desktop Support | T67: Desktop Support | U67: Lisa Kumar | V67: Deepika Singh | W67: 2025-01-07 11:09:17 | X67: 2026-04-30 11:09:17 | Y67: ServiceNow Discovery | Z67: Workday | AA67: Time & Attendance | AB67: Workday Time Tracking | AC67: Tenant API Gateway | AD67: 90 | AE67: Compliant | AF67: Missing manufacturer
A68: 6b25a72c61a341fa801e3275aaddf409 | B68: PC-0100028 | C68: cmdb_ci_pc_hardware | D68: AST-84686540 | E68: SN6520956207 | F68: Lenovo | G68: ThinkPad X1 Carbon | H68: Hyderabad-DC1 | I68: Production | J68: Installed | K68: Operational | L68: 10.20.136.200 | O68: 6 | P68: 8 | Q68: 512 | R68: Kavita Williams | S68: IT Service Desk | T68: IT Service Desk | U68: Arjun Patel | V68: Vikram Rao | W68: 2023-11-16 11:09:17 | X68: 2026-05-16 11:09:17 | Y68: CSV Import | Z68: Microsoft 365 | AA68: Enterprise Email | AB68: Microsoft Teams | AC68: Entra ID (Azure AD) | AD68: 100 | AE68: Compliant | AF68: None
A69: 01eef4710b974cf88dd444c7ef894c5e | B69: lnx-tst-new-00010 | C69: cmdb_ci_linux_server | D69: AST-13498352 | E69: SN7936591952 | F69: Lenovo | H69: New York-DC | I69: Test | J69: Installed | L69: 10.92.116.132 | M69: Red Hat Enterprise Linux | N69: 9.2 | O69: 4 | P69: 64 | Q69: 1000 | S69: Linux Admins | T69: Linux Admins | U69: Deepika Jones | V69: Priya Jones | W69: 2025-10-27 11:09:17 | X69: 2025-03-03 11:09:17 | Y69: Service Mapping | Z69: Adobe | AA69: Content Authoring | AB69: Adobe Creative Cloud | AC69: Adobe Cloud Storage | AD69: 70 | AE69: Partially Compliant | AF69: Missing model_id; Missing operational_status; Stale discovery (>90 days)
A70: 410fcb22ae3842908be64357b84110c3 | B70: PC-0100029 | C70: cmdb_ci_pc_hardware | D70: AST-28307904 | F70: Apple | G70: MacBook Pro 14" | H70: Singapore-DC | I70: Production | J70: Installed | K70: Operational | L70: 10.48.203.159 | O70: 6 | P70: 8 | Q70: 512 | R70: Rohit Iyer | S70: Desktop Support | T70: Desktop Support | U70: Mary Jones | V70: David Wilson | W70: 2023-06-17 11:09:17 | X70: 2026-05-10 11:09:17 | Y70: BMC ADDM | Z70: SAP ERP | AA70: Order-to-Cash | AB70: SAP Fiori Launchpad | AC70: SAP NetWeaver Application Server | AD70: 90 | AE70: Compliant | AF70: Missing serial_number
A71: bae5aafcd65b483d99c24b39f8a19964 | B71: PC-0100030 | C71: cmdb_ci_pc_hardware | D71: AST-71551117 | E71: SN7852631510 | F71: Dell | G71: OptiPlex 7090 | H71: Hyderabad-DC1 | I71: DR | J71: Installed | K71: Operational | L71: 10.136.43.6 | O71: 6 | P71: 16 | Q71: 512 | R71: Karthik Reddy | S71: End User Computing | T71: End User Computing | U71: Anjali Reddy | V71: Rajesh Desai | W71: 2025-01-16 11:09:17 | X71: 2026-05-01 11:09:17 | Y71: Manual | Z71: Microsoft 365 | AA71: Document Collaboration | AB71: Power Platform | AC71: Microsoft Graph API | AD71: 100 | AE71: Compliant | AF71: None
A72: 3d0ce8ae2cd142e587cebb3305374408 | B72: PC-0100031 | C72: cmdb_ci_pc_hardware | D72: AST-13281401 | E72: SN4112603528 | F72: Lenovo | G72: ThinkPad X1 Carbon | H72: Mumbai-DC2 | I72: Development | J72: Installed | K72: Operational | L72: 10.160.58.211 | O72: 8 | P72: 8 | Q72: 512 | R72: Priya Pillai | S72: IT Service Desk | U72: Emma Sharma | V72: Arjun Shetty | W72: 2024-01-10 11:09:17 | X72: 2026-05-06 11:09:17 | Y72: BMC ADDM | Z72: Microsoft 365 | AA72: File Storage & Sync | AB72: SharePoint Online | AC72: Exchange Transport Service | AD72: 90 | AE72: Compliant | AF72: Missing support_group
A73: afa8d80708d442aa9d9dc55584fdf6fc | B73: PC-0100032 | C73: cmdb_ci_pc_hardware | D73: AST-55209152 | E73: SN2912633192 | F73: HP | G73: EliteBook 840 G10 | H73: Dubai-DC | I73: Production | J73: Installed | K73: Operational | L73: 10.15.151.119 | O73: 4 | P73: 16 | Q73: 256 | R73: Deepika Shetty | S73: IT Service Desk | T73: IT Service Desk | U73: Vikram Taylor | V73: Rajesh Brown | W73: 2024-08-23 11:09:17 | X73: 2026-04-30 11:09:17 | Y73: Service Mapping | Z73: Adobe | AA73: Web Analytics | AB73: Adobe Analytics | AC73: Adobe Asset Service | AD73: 100 | AE73: Compliant | AF73: None
A74: 3346ee78dfeb48259466b3c826e62822 | B74: db-prd-ben-00002 | C74: cmdb_ci_db_instance | D74: AST-92855343 | E74: SN9740253467 | F74: MongoDB Inc. | G74: MongoDB 7.0 | H74: Bengaluru-DC2 | I74: Production | J74: Installed | K74: Operational | L74: 10.35.11.239 | O74: 16 | P74: 32 | Q74: 2000 | S74: DBA - Oracle | T74: DBA - Oracle | U74: Shreya Iyer | V74: Karthik Verma | W74: 2023-10-11 11:09:17 | X74: 2024-12-31 11:09:17 | Y74: CSV Import | Z74: Oracle Fusion ERP | AA74: Risk & Compliance | AB74: Oracle Fusion Procurement | AC74: Oracle Identity Cloud Service | AD74: 90 | AE74: Compliant | AF74: Stale discovery (>90 days)
A75: 58443120374746cfbc9065b133183a7d | B75: vm-tst-sin-00011 | C75: cmdb_ci_vmware_instance | D75: AST-52780809 | E75: SN8998540083 | F75: VMware | G75: vSphere VM | H75: Singapore-DC | I75: Test | J75: Installed | K75: Operational | L75: 10.99.233.63 | M75: Windows Server | N75: 2019 Standard | O75: 64 | P75: 768 | Q75: 4000 | S75: Cloud Operations | T75: Cloud Operations | U75: Pooja Sharma | V75: Aditya Banerjee | W75: 2022-05-28 11:09:17 | X75: 2026-05-02 11:09:17 | Y75: ServiceNow Discovery | Z75: Workday | AA75: Time & Attendance | AB75: Workday Time Tracking | AC75: Identity Federation (SAML) | AD75: 100 | AE75: Compliant | AF75: None
A76: fc85ac0cdcf1420398746613f84d2cd2 | B76: PC-0100033 | C76: cmdb_ci_pc_hardware | D76: AST-28894563 | E76: SN5972008909 | F76: Dell | G76: OptiPlex 7090 | H76: Mumbai-DC1 | I76: Development | J76: Installed | L76: 10.179.126.19 | O76: 4 | P76: 8 | Q76: 512 | R76: Karthik Sharma | S76: End User Computing | T76: End User Computing | U76: Karthik Banerjee | V76: Deepika Wilson | W76: 2022-06-07 11:09:17 | X76: 2026-05-20 11:09:17 | Y76: Service Mapping | Z76: Microsoft 365 | AA76: File Storage & Sync | AB76: SharePoint Online | AC76: M365 Defender | AD76: 90 | AE76: Compliant | AF76: Missing operational_status
A77: 5fae79cbd31242818a0e1c33017e585d | B77: lnx-dev-lon-00011 | C77: cmdb_ci_linux_server | D77: AST-89064264 | E77: SN7503746539 | F77: Cisco | G77: UCS C220 M6 | H77: London-DR | I77: Development | J77: Retired | K77: Operational | L77: 10.153.196.89 | M77: Red Hat Enterprise Linux | N77: 9.2 | O77: 8 | P77: 16 | Q77: 1000 | S77: Unix Operations | T77: Unix Operations | U77: Rohit Smith | V77: Rajesh Jones | W77: 2023-10-01 11:09:17 | X77: 2025-12-09 11:09:17 | Y77: CSV Import | Z77: Oracle Fusion ERP | AA77: Treasury Operations | AB77: Oracle Fusion Risk Mgmt | AC77: Oracle Analytics Cloud | AD77: 90 | AE77: Compliant | AF77: Stale discovery (>90 days)
A78: 7d7fc7b18e2c4a758e7401f609318552 | B78: PC-0100034 | C78: cmdb_ci_pc_hardware | D78: AST-48362253 | E78: SN7859710035 | F78: Dell | G78: OptiPlex 7090 | H78: Mumbai-DC1 | I78: Development | J78: Retired | K78: Operational | L78: 10.124.62.12 | O78: 6 | P78: 8 | Q78: 512 | R78: Anand Reddy | S78: IT Service Desk | T78: IT Service Desk | U78: Lakshmi Taylor | V78: Deepika Verma | W78: 2025-06-28 11:09:17 | X78: 2026-05-11 11:09:17 | Y78: Manual | Z78: Microsoft 365 | AA78: Enterprise Email | AB78: Microsoft Purview | AC78: Microsoft Graph API | AD78: 100 | AE78: Compliant | AF78: None
A79: 9b18f3f879a3460f9bf3878f5fc3c73c | B79: PC-0100035 | C79: cmdb_ci_pc_hardware | D79: AST-58085603 | E79: SN2965142575 | F79: Lenovo | G79: ThinkPad X1 Carbon | H79: New York-DC | J79: In Stock | K79: Operational | L79: 10.32.205.117 | O79: 6 | P79: 32 | Q79: 512 | R79: Arjun Banerjee | S79: Desktop Support | T79: Desktop Support | U79: Ravi Pillai | V79: Michael Singh | W79: 2025-05-08 11:09:17 | X79: 2026-05-19 11:09:17 | Y79: Service Mapping | Z79: Microsoft 365 | AA79: Document Collaboration | AB79: Microsoft Teams | AC79: Entra ID (Azure AD) | AD79: 90 | AE79: Compliant | AF79: Missing environment
A80: 532985fe22f44da1af2fcbfe13c41fd1 | B80: lnx-prd-pun-00012 | C80: cmdb_ci_linux_server | D80: AST-89531618 | E80: SN7304214389 | F80: HPE | G80: ProLiant DL380 Gen10 | I80: Production | J80: Installed | K80: DR Standby | L80: 10.19.189.253 | M80: Ubuntu | N80: 20.04 LTS | O80: 64 | P80: 384 | Q80: 4000 | S80: Unix Operations | T80: Unix Operations | U80: James Patel | V80: Shreya Banerjee | W80: 2025-10-19 11:09:17 | X80: 2026-05-21 11:09:17 | Y80: BMC ADDM | Z80: SAP ERP | AA80: Production Planning | AB80: SAP S/4HANA Finance | AC80: SAP PI/PO Integration | AD80: 90 | AE80: Compliant | AF80: Missing location
A81: f487e8fe8e7d402bbf4fb86b94fd409b | B81: PC-0100036 | C81: cmdb_ci_pc_hardware | D81: AST-62169641 | E81: SN7446187381 | F81: Lenovo | G81: ThinkPad X1 Carbon | H81: London-DR | I81: Production | J81: Installed | K81: Operational | L81: 10.49.240.192 | O81: 8 | P81: 8 | Q81: 1000 | R81: Robert Singh | S81: End User Computing | T81: End User Computing | U81: John Rao | V81: Michael Patel | W81: 2022-07-23 11:09:17 | X81: 2026-05-15 11:09:17 | Y81: SCCM | Z81: Adobe | AA81: Digital Asset Management | AB81: Adobe Campaign | AC81: Adobe Cloud Storage | AD81: 100 | AE81: Compliant | AF81: None
A82: 5b616bb02b804e16ba938892f72349e3 | B82: win-tst-ben-00008 | C82: cmdb_ci_win_server | D82: AST-30771170 | E82: SN1833919749 | F82: Dell EMC | G82: PowerEdge R650 | I82: Test | K82: Operational | L82: 10.101.132.81 | M82: Windows Server | N82: 2022 Standard | O82: 64 | P82: 256 | Q82: 16000 | S82: Wintel Operations | T82: Wintel Operations | U82: James Banerjee | V82: Mary Williams | W82: 2024-08-09 11:09:17 | X82: 2025-01-02 11:09:17 | Y82: BMC ADDM | Z82: Microsoft 365 | AA82: Document Collaboration | AB82: OneDrive for Business | AC82: Entra ID (Azure AD) | AD82: 70 | AE82: Partially Compliant | AF82: Missing location; Missing install_status; Stale discovery (>90 days)
A83: 99af134ea8cf4258aa87a562b764b5f8 | B83: app-uat-dub-00005 | C83: cmdb_ci_app_server | D83: AST-26820801 | E83: SN9016191944 | F83: IBM | G83: WebSphere 9.0 | H83: Dubai-DC | I83: UAT | J83: Installed | K83: Operational | L83: 10.162.188.163 | O83: 4 | P83: 512 | Q83: 200 | S83: Java Platform Team | T83: Java Platform Team | U83: Deepika Brown | V83: Sunita Kumar | W83: 2022-05-22 11:09:17 | X83: 2026-05-06 11:09:17 | Y83: Manual | Z83: Workday | AA83: Payroll Processing | AB83: Workday Time Tracking | AC83: Tenant API Gateway | AD83: 100 | AE83: Compliant | AF83: None
A84: 8feb751784654624947c249e0ff72c75 | B84: vm-prd-mum-00012 | C84: cmdb_ci_vmware_instance | D84: AST-32235982 | E84: SN3353503747 | F84: VMware | G84: vSphere VM | H84: Mumbai-DC2 | I84: Production | J84: Installed | K84: Operational | L84: 10.42.251.160 | M84: Red Hat Enterprise Linux | N84: 8.6 | O84: 32 | P84: 64 | Q84: 2000 | S84: Virtualization Team | T84: Virtualization Team | U84: Anand Krishnan | V84: Arjun Kumar | W84: 2026-02-12 11:09:17 | X84: 2025-01-23 11:09:17 | Y84: ServiceNow Discovery | Z84: Oracle Fusion ERP | AA84: Treasury Operations | AB84: Oracle Fusion Risk Mgmt | AC84: Oracle REST Data Service | AD84: 90 | AE84: Compliant | AF84: Stale discovery (>90 days)
A85: 3a671914251c4feda3b0d826c2416593 | B85: win-prd-sin-00009 | C85: cmdb_ci_win_server | D85: AST-98382792 | F85: HPE | I85: Production | J85: Installed | K85: Operational | L85: 10.18.75.84 | M85: Windows Server | N85: 2019 Datacenter | O85: 24 | P85: 128 | Q85: 500 | S85: Platform Engineering | T85: Platform Engineering | V85: Sarah Patel | W85: 2022-08-12 11:09:17 | X85: 2026-05-05 11:09:17 | Y85: Service Mapping | Z85: Oracle Fusion ERP | AA85: Risk & Compliance | AB85: Oracle Fusion Tax Reporting | AC85: Oracle Autonomous Database | AD85: 60 | AE85: Partially Compliant | AF85: Missing serial_number; Missing model_id; Missing owned_by; Missing location
A86: 6257092f2ccf4b9987f50054662699bb | B86: PC-0100037 | C86: cmdb_ci_pc_hardware | D86: AST-16717998 | E86: SN3742444175 | F86: Lenovo | G86: ThinkPad X1 Carbon | H86: Bengaluru-DC1 | I86: Production | J86: Installed | K86: Operational | L86: 10.46.40.103 | O86: 4 | P86: 32 | Q86: 1000 | R86: Meera Kumar | S86: IT Service Desk | T86: IT Service Desk | U86: Arjun Taylor | V86: Rajesh Reddy | W86: 2022-12-05 11:09:17 | X86: 2026-05-05 11:09:17 | Y86: ServiceNow Discovery | Z86: Microsoft 365 | AA86: Video Conferencing | AB86: Microsoft Teams | AC86: M365 Defender | AD86: 100 | AE86: Compliant | AF86: None
A87: 4fa10b37b49b45ae8480298449a0604d | B87: PC-0100038 | C87: cmdb_ci_pc_hardware | D87: AST-58057168 | E87: SN9152960694 | F87: Apple | G87: MacBook Pro 14" | H87: Mumbai-DC2 | I87: Production | J87: Installed | K87: Operational | L87: 10.19.75.114 | O87: 4 | P87: 32 | Q87: 256 | R87: Arjun Pillai | S87: End User Computing | T87: End User Computing | U87: Neha Singh | V87: David Desai | W87: 2025-06-19 11:09:17 | X87: 2026-05-03 11:09:17 | Y87: Manual | Z87: Adobe | AA87: Digital Asset Management | AB87: Adobe Campaign | AC87: Adobe Identity Management Service | AD87: 100 | AE87: Compliant | AF87: None
A88: 9831f465fefd46bd8b61a80d390c46ef | B88: PC-0100039 | C88: cmdb_ci_pc_hardware | E88: SN4181787600 | F88: Lenovo | G88: ThinkPad X1 Carbon | H88: New York-DC | I88: Development | J88: Installed | K88: Operational | L88: 10.91.218.250 | O88: 6 | P88: 32 | Q88: 1000 | R88: Shreya Sharma | S88: IT Service Desk | T88: IT Service Desk | V88: Emma Joshi | W88: 2023-03-19 11:09:17 | X88: 2026-05-08 11:09:17 | Y88: Service Mapping | Z88: Microsoft 365 | AA88: Document Collaboration | AB88: Microsoft Teams | AC88: Entra ID (Azure AD) | AD88: 80 | AE88: Compliant | AF88: Missing owned_by; Missing asset_tag
A89: 6d5e48a336034b7ab28c947ee04ed842 | B89: PC-0100040 | C89: cmdb_ci_pc_hardware | D89: AST-72274867 | E89: SN1235104947 | F89: Apple | G89: MacBook Pro 14" | H89: Gurgaon-Office | I89: UAT | J89: In Maintenance | L89: 10.171.201.244 | O89: 4 | P89: 32 | Q89: 1000 | R89: Rohit Wilson | S89: Desktop Support | T89: Desktop Support | U89: Kavita Iyer | V89: David Pillai | W89: 2025-10-29 11:09:17 | X89: 2024-10-20 11:09:17 | Y89: CSV Import | Z89: Microsoft 365 | AA89: Document Collaboration | AB89: Microsoft Teams | AC89: Entra ID (Azure AD) | AD89: 80 | AE89: Compliant | AF89: Missing operational_status; Stale discovery (>90 days)
A90: e2109e1728aa43c98558f84ac4958350 | B90: lnx-tst-dub-00013 | C90: cmdb_ci_linux_server | D90: AST-75554065 | E90: SN4333104905 | F90: HPE | G90: ProLiant DL380 Gen10 | H90: Dubai-DC | I90: Test | J90: Installed | L90: 10.72.34.136 | M90: Ubuntu | N90: 22.04 LTS | O90: 8 | P90: 128 | Q90: 200 | S90: Platform Engineering | T90: Platform Engineering | V90: Vikram Smith | W90: 2025-02-21 11:09:17 | X90: 2026-05-19 11:09:17 | Y90: CSV Import | Z90: SAP ERP | AA90: Procure-to-Pay | AB90: SAP S/4HANA Sales | AC90: SAP NetWeaver Application Server | AD90: 80 | AE90: Compliant | AF90: Missing owned_by; Missing operational_status
A91: c12247ce14164c38ba030045dcf77ddf | B91: app-pre-che-00006 | C91: cmdb_ci_app_server | D91: AST-20089617 | G91: Tomcat 10 | H91: Chennai-DC1 | I91: Pre-Production | J91: Installed | L91: 10.90.99.110 | O91: 96 | P91: 256 | Q91: 500 | S91: Java Platform Team | U91: Karthik Jones | V91: Vikram Smith | W91: 2024-04-14 11:09:17 | X91: 2025-10-26 11:09:17 | Y91: BMC ADDM | Z91: Oracle Fusion ERP | AA91: Treasury Operations | AB91: Oracle Fusion Risk Mgmt | AC91: Oracle Analytics Cloud | AD91: 50 | AE91: Non-Compliant | AF91: Missing manufacturer; Missing operational_status; Missing serial_number; Missing support_group; Stale discovery (>90 days)
A92: 9a1e532dfb4e433ba1ade44f721fceff | B92: PC-0100041 | C92: cmdb_ci_pc_hardware | D92: AST-92662551 | E92: SN7479292853 | F92: Dell | G92: Latitude 5540 | H92: Chennai-DC1 | I92: Production | J92: In Maintenance | K92: Operational | L92: 10.11.106.82 | O92: 6 | P92: 8 | Q92: 256 | R92: Deepika Brown | S92: End User Computing | T92: End User Computing | U92: Lakshmi Verma | V92: Neha Smith | W92: 2024-11-09 11:09:17 | X92: 2026-05-09 11:09:17 | Y92: BMC ADDM | Z92: Microsoft 365 | AA92: File Storage & Sync | AB92: SharePoint Online | AC92: Microsoft Endpoint Manager | AD92: 100 | AE92: Compliant | AF92: None
A93: 977df5352a584508bd113881d84a3a31 | B93: lnx-dev-dub-00014 | C93: cmdb_ci_linux_server | D93: AST-78036374 | E93: SN1354154721 | F93: Dell EMC | G93: PowerEdge R650 | H93: Dubai-DC | I93: Development | J93: Installed | K93: Operational | L93: 10.73.127.12 | M93: Red Hat Enterprise Linux | N93: 8.6 | O93: 4 | P93: 384 | Q93: 16000 | S93: Platform Engineering | T93: Platform Engineering | U93: Rajesh Wilson | V93: David Rao | W93: 2025-03-02 11:09:17 | X93: 2026-05-12 11:09:17 | Y93: Manual | Z93: Microsoft 365 | AA93: Internal Communications | AB93: OneDrive for Business | AC93: Microsoft Graph API | AD93: 100 | AE93: Compliant | AF93: None
A94: 5c917e8d081943f7bc8c9e12e239d5e4 | B94: web-dev-lon-00003 | C94: cmdb_ci_web_server | D94: AST-90025739 | E94: SN7642174299 | H94: London-DR | I94: Development | J94: Installed | K94: Operational | L94: 10.113.83.45 | O94: 8 | P94: 512 | Q94: 200 | S94: Middleware Admins | T94: Middleware Admins | U94: Anjali Jones | V94: Kavita Wilson | W94: 2025-08-19 11:09:17 | X94: 2026-04-29 11:09:17 | Y94: CSV Import | Z94: SAP ERP | AA94: Inventory & Warehouse | AB94: SAP Fiori Launchpad | AC94: SAP PI/PO Integration | AD94: 80 | AE94: Compliant | AF94: Missing manufacturer; Missing model_id
A95: 118e806c69614fcba5e4fafa630ab92b | B95: db-uat-pun-00003 | C95: cmdb_ci_db_instance | D95: AST-74332438 | E95: SN1786560424 | F95: Microsoft | G95: SQL Server 2022 | H95: Pune-Office | I95: UAT | J95: Installed | K95: Repair in Progress | L95: 10.169.102.41 | O95: 24 | P95: 256 | Q95: 8000 | S95: DBA - SQL Server | T95: DBA - SQL Server | U95: Rohit Rao | V95: Emma Sharma | W95: 2025-09-27 11:09:17 | X95: 2026-05-23 11:09:17 | Y95: Service Mapping | Z95: SAP ERP | AA95: Procure-to-Pay | AB95: SAP S/4HANA Production | AC95: SAP NetWeaver Application Server | AD95: 100 | AE95: Compliant | AF95: None
A96: 09dd89821eb34b38806e09bf872e0565 | B96: lnx-dev-pun-00015 | C96: cmdb_ci_linux_server | D96: AST-27215508 | E96: SN7932356344 | F96: Lenovo | G96: ThinkSystem SR650 | H96: Pune-Office | I96: Development | J96: Installed | K96: Operational | L96: 10.109.235.118 | M96: Ubuntu | N96: 22.04 LTS | O96: 8 | P96: 384 | Q96: 4000 | S96: Linux Admins | T96: Linux Admins | U96: Karthik Wilson | V96: Sarah Verma | W96: 2025-09-20 11:09:17 | X96: 2026-05-10 11:09:17 | Y96: CSV Import | Z96: SAP ERP | AA96: Inventory & Warehouse | AB96: SAP S/4HANA Sales | AC96: SAP NetWeaver Application Server | AD96: 100 | AE96: Compliant | AF96: None
A97: 19f0f2938b8f4a53b27f87a70520d94e | B97: PC-0100042 | C97: cmdb_ci_pc_hardware | D97: AST-61580157 | E97: SN8397240769 | F97: Lenovo | G97: ThinkPad T14 | H97: London-DR | I97: Pre-Production | J97: In Stock | K97: Operational | L97: 10.82.129.183 | O97: 6 | P97: 32 | Q97: 256 | R97: Anjali Shetty | S97: IT Service Desk | T97: IT Service Desk | U97: Pooja Kumar | V97: Kavita Patel | W97: 2024-05-11 11:09:17 | X97: 2026-05-06 11:09:17 | Y97: BMC ADDM | Z97: Adobe | AA97: Digital Asset Management | AB97: Adobe Campaign | AC97: Adobe API Gateway | AD97: 100 | AE97: Compliant | AF97: None
A98: ffa7c11185fa4ebfbc4013f5be6a8060 | B98: PC-0100043 | C98: cmdb_ci_pc_hardware | D98: AST-17043135 | E98: SN6769288510 | F98: Apple | G98: MacBook Pro 14" | H98: Chennai-DC1 | I98: Pre-Production | K98: Operational | L98: 10.89.94.195 | O98: 8 | P98: 8 | Q98: 512 | R98: John Pillai | S98: Desktop Support | T98: Desktop Support | U98: Rajesh Taylor | V98: Sarah Verma | W98: 2025-02-10 11:09:17 | X98: 2026-05-06 11:09:17 | Y98: Manual | Z98: Microsoft 365 | AA98: File Storage & Sync | AB98: Exchange Online | AC98: Exchange Transport Service | AD98: 90 | AE98: Compliant | AF98: Missing install_status
A99: 8298f36a8d864901afd8f22471f46ace | B99: app-prd-ben-00007 | C99: cmdb_ci_app_server | E99: SN1818946952 | F99: Apache Foundation | G99: Tomcat 10 | H99: Bengaluru-DC2 | J99: Installed | L99: 10.24.9.245 | O99: 16 | P99: 768 | Q99: 16000 | S99: Java Platform Team | T99: Java Platform Team | U99: Shreya Banerjee | V99: Anjali Verma | W99: 2025-06-17 11:09:17 | X99: 2026-05-18 11:09:17 | Y99: CSV Import | Z99: Microsoft 365 | AA99: Enterprise Email | AB99: OneDrive for Business | AC99: Microsoft Graph API | AD99: 70 | AE99: Partially Compliant | AF99: Missing asset_tag; Missing operational_status; Missing environment
A100: e547aee8914848abb72bd862ef4fbde0 | B100: PC-0100044 | C100: cmdb_ci_pc_hardware | D100: AST-94642781 | E100: SN6970168950 | F100: Lenovo | H100: London-DR | I100: Production | J100: Installed | K100: DR Standby | L100: 10.30.27.9 | O100: 6 | P100: 8 | Q100: 512 | R100: Kavita Brown | S100: Desktop Support | U100: Anand Joshi | V100: Anjali Joshi | W100: 2025-04-06 11:09:17 | X100: 2026-05-23 11:09:17 | Y100: Manual | Z100: Microsoft 365 | AA100: Document Collaboration | AB100: OneDrive for Business | AC100: Microsoft Endpoint Manager | AD100: 80 | AE100: Compliant | AF100: Missing model_id; Missing support_group
...

Sheet CSDM v5 Mapping
A1: CSDM v5 Application & Service Mapping
A3: How the 5 Business Applications map to Business Services, Technical Applications, and Technical Services
A5: Business Application | B5: Business Services | C5: Technical Applications | D5: Technical Services
A6: Workday | B6: HR Self-Service • Talent Acquisition • Payroll Processing • Time & Attendance | C6: Workday HCM Core • Workday Payroll Engine • Workday Recruiting Portal • Workday Time Tracking • Workday Benefits Admin | D6: Identity Federation (SAML) • HR Data Integration Bus • Tenant API Gateway • Workday Reporting Service
A7: SAP ERP | B7: Order-to-Cash • Procure-to-Pay • Record-to-Report • Inventory & Warehouse • Production Planning | C7: SAP S/4HANA Finance • SAP S/4HANA Logistics • SAP S/4HANA Sales • SAP S/4HANA Procurement • SAP S/4HANA Production • SAP Fiori Launchpad | D7: SAP HANA Database • SAP NetWeaver Application Server • SAP Solution Manager • SAP Gateway OData Service • SAP PI/PO Integration
A8: Microsoft 365 | B8: Enterprise Email • Document Collaboration • Video Conferencing • Internal Communications • File Storage & Sync | C8: Exchange Online • SharePoint Online • Microsoft Teams • OneDrive for Business • Power Platform • Microsoft Purview | D8: Entra ID (Azure AD) • Microsoft Graph API • Exchange Transport Service • M365 Defender • Microsoft Endpoint Manager
A9: Adobe | B9: Content Authoring • Digital Asset Management • Marketing Automation • Web Analytics | C9: Adobe Creative Cloud • Adobe Experience Manager • Adobe Campaign • Adobe Analytics • Adobe Workfront | D9: Adobe Identity Management Service • Adobe Asset Service • Adobe Cloud Storage • Adobe API Gateway
A10: Oracle Fusion ERP | B10: Financial Close • Procurement Operations • Project Portfolio Mgmt • Risk & Compliance • Treasury Operations | C10: Oracle Fusion Financials • Oracle Fusion Procurement • Oracle Fusion Project Mgmt • Oracle Fusion Risk Mgmt • Oracle Fusion Tax Reporting | D10: Oracle Autonomous Database • Oracle Identity Cloud Service • Oracle Integration Cloud • Oracle Analytics Cloud • Oracle REST Data Service
A13: CSDM v5 5-Tier Alignment
A14: Tier 1 — Business Capability | B14: Strategic capability the organization needs (HR Operations, Finance Operations, etc.)
A15: Tier 2 — Business Application | B15: Workday, SAP ERP, Microsoft 365, Adobe, Oracle Fusion ERP (the 5 in this dataset)
A16: Tier 3 — Application Service / Technical Application | B16: cmdb_ci_service_auto — the runnable application service (e.g. SAP S/4HANA Finance)
A17: Tier 4 — Dynamic CI Group | B17: Query-based membership of supporting CIs (inferred from environment+application)
A18: Tier 5 — Component CIs | B18: The technical inventory rows in CMDB CIs sheet — servers, DBs, network, storage, PCs
A19: Business Service | B19: What the business consumer perceives (HR Self-Service, Order-to-Cash, etc.)
A20: Technical Service | B20: Underlying technical capability that supports the Business Service (Identity Federation, API Gateway, etc.)
